guesstime/__init__.py
guesstime/filters.py
guesstime/time_decode.py
guesstime/version.py
guesstime/pyunit_time/__init__.py
guesstime/pyunit_time/filters.py
guesstime/pyunit_time/observer.py
guesstime/pyunit_time/pytime.py
guesstime/pyunit_time/re.txt
guesstime/pyunit_time/pyunit_calendar/CTC_.py
guesstime/pyunit_time/pyunit_calendar/LSC.py
guesstime/pyunit_time/pyunit_calendar/SC_.py
guesstime/pyunit_time/pyunit_calendar/__init__.py
guesstime/pyunit_time/pyunit_calendar/batchcalendar.py
guesstime/pyunit_time/pyunit_calendar/config.py
guesstime/pyunit_time/pyunit_calendar/date.zip
guesstime/pyunit_time/retime/__init__.py
guesstime/pyunit_time/retime/days.py
guesstime/pyunit_time/retime/formats.py
guesstime/pyunit_time/retime/hours.py
guesstime/pyunit_time/retime/lunarholiday.py
guesstime/pyunit_time/retime/minutes.py
guesstime/pyunit_time/retime/months.py
guesstime/pyunit_time/retime/seconds.py
guesstime/pyunit_time/retime/solarholiday.py
guesstime/pyunit_time/retime/solarterm24.py
guesstime/pyunit_time/retime/specialholiday.py
guesstime/pyunit_time/retime/weeks.py
guesstime/pyunit_time/retime/years.py
guesstime-1.1.4.dist-info/LICENSE
guesstime-1.1.4.dist-info/METADATA
guesstime-1.1.4.dist-info/WHEEL
guesstime-1.1.4.dist-info/top_level.txt
guesstime-1.1.4.dist-info/zip-safe
guesstime-1.1.4.dist-info/RECORD
