Metadata-Version: 2.1
Name: guesstime
Version: 1.1.4
Summary: guesstime
Home-page: https://github.com/DJMIN/dao
Author: readerror
Author-email: readerror@sina.com
Maintainer: readerror
Maintainer-email: readerror@sina.com
License: GPL License
Platform: all
Requires-Python: >=3.5
License-File: LICENSE
Requires-Dist: wrapt
Requires-Dist: wheel
Requires-Dist: twine
Requires-Dist: python-dateutil
Requires-Dist: arrow (~=1.2.2)
Requires-Dist: pytz
